{
  "@context": "http://iiif.io/api/presentation/3/context.json",
  "id": "https://markpbaggett.github.io/corpora-service-maps/manifests/66d0d20eec007cec424f61cc.json",
  "type": "Manifest",
  "label": {
    "en": [
      "VII Corps"
    ]
  },
  "metadata": [
    {
      "label": {
        "en": [
          "description"
        ]
      },
      "value": {
        "en": [
          "Route map with operational details"
        ]
      }
    },
    {
      "label": {
        "en": [
          "unit"
        ]
      },
      "value": {
        "en": [
          "VII Corps"
        ]
      }
    },
    {
      "label": {
        "en": [
          "id"
        ]
      },
      "value": {
        "en": [
          "66d0d20eec007cec424f61cc"
        ]
      }
    }
  ],
  "thumbnail": [
    {
      "id": "https://strob6zro3bzklrulaqu2545sy0odbvz.lambda-url.us-east-2.on.aws/iiif/3/7-26-2023/VII-Corps.jpg",
      "type": "Image"
    }
  ],
  "partOf": [
    {
      "id": "https://markpbaggett.github.io/corpora-service-maps/collections/collection.json",
      "type": "Collection"
    }
  ],
  "items": [
    {
      "id": "https://markpbaggett.github.io/corpora-service-maps/66d0d20eec007cec424f61cc/canvas/1",
      "type": "Canvas",
      "label": {
        "en": [
          "Canvas for VII Corps"
        ]
      },
      "height": 14344,
      "width": 18000,
      "thumbnail": [
        {
          "id": "https://strob6zro3bzklrulaqu2545sy0odbvz.lambda-url.us-east-2.on.aws/iiif/3/7-26-2023/VII-Corps.jpg/full/562,/0/default.jpg",
          "type": "Image",
          "height": 448,
          "width": 562,
          "service": [
            {
              "id": "https://strob6zro3bzklrulaqu2545sy0odbvz.lambda-url.us-east-2.on.aws/iiif/3/7-26-2023/VII-Corps.jpg",
              "type": "ImageService3",
              "profile": "level2"
            }
          ],
          "format": "image/jpeg"
        }
      ],
      "items": [
        {
          "id": "https://markpbaggett.github.io/corpora-service-maps/66d0d20eec007cec424f61cc/canvas/1/annotation/1/page/1",
          "type": "AnnotationPage",
          "items": [
            {
              "id": "https://markpbaggett.github.io/corpora-service-maps/66d0d20eec007cec424f61cc/canvas/1/annotation/1",
              "type": "Annotation",
              "motivation": "painting",
              "body": {
                "id": "https://strob6zro3bzklrulaqu2545sy0odbvz.lambda-url.us-east-2.on.aws/iiif/3/7-26-2023/VII-Corps.jpg/full/max/0/default.jpg",
                "type": "Image",
                "height": 14344,
                "width": 18000,
                "service": [
                  {
                    "id": "https://strob6zro3bzklrulaqu2545sy0odbvz.lambda-url.us-east-2.on.aws/iiif/3/7-26-2023/VII-Corps.jpg",
                    "type": "ImageService3",
                    "profile": "level2"
                  }
                ],
                "format": "image/jpeg"
              },
              "target": "https://markpbaggett.github.io/corpora-service-maps/66d0d20eec007cec424f61cc/canvas/1"
            }
          ]
        }
      ]
    }
  ]
}